dash_local_react_components/__init__.py
dash_local_react_components/_common.py
dash_local_react_components/_config.py
dash_local_react_components/_file_generator.py
dash_local_react_components/_functions.py
dash_local_react_components/_types.py
dash_local_react_components/_utils.py
dash_local_react_components-1.4.0.dist-info/LICENSE
dash_local_react_components-1.4.0.dist-info/METADATA
dash_local_react_components-1.4.0.dist-info/WHEEL
dash_local_react_components-1.4.0.dist-info/top_level.txt
dash_local_react_components-1.4.0.dist-info/RECORD
